Metadata-Version: 2.2
Name: ANGIE3Dpy
Version: 0.1.6
Summary: My short description for my project.
Home-page: https://?
Author: Xiaolei Li
Author-email: xzl0125@auburn.edu
License: MIT
Classifier: License :: OSI Approved :: MIT License
Classifier: Programming Language :: Python
Classifier: Programming Language :: Python :: 3
Classifier: Programming Language :: Python :: 3.6
Classifier: Programming Language :: Python :: Implementation :: CPython
Classifier: Programming Language :: Python :: Implementation :: PyPy
Requires-Python: >=3.6.0
License-File: LICENSE.txt
Requires-Dist: matplotlib
Requires-Dist: numpy
Requires-Dist: netCDF4
Requires-Dist: Cartopy
Requires-Dist: scipy
Dynamic: author
Dynamic: author-email
Dynamic: classifier
Dynamic: description
Dynamic: description-content-type
Dynamic: home-page
Dynamic: license
Dynamic: requires-dist
Dynamic: requires-python
Dynamic: summary
